MANIFEST.in
README.rst
setup.py
TestPackageQSC/abcd.py
TestPackageQSC.egg-info/PKG-INFO
TestPackageQSC.egg-info/SOURCES.txt
TestPackageQSC.egg-info/dependency_links.txt
TestPackageQSC.egg-info/top_level.txt
TestPackageQSC.egg-info/zip-safe